xaal/__init__.py
xaal/fuse/__init__.py
xaal/fuse/mount.py
xaal_fuse-0.4.2.dist-info/METADATA
xaal_fuse-0.4.2.dist-info/WHEEL
xaal_fuse-0.4.2.dist-info/entry_points.txt
xaal_fuse-0.4.2.dist-info/top_level.txt
xaal_fuse-0.4.2.dist-info/RECORD
