Metadata-Version: 2.4
Name: xaal.fuse
Version: 0.4.2
Summary: xAAL Fuse filesystem
Author-email: Jerome Kerdreux <Jerome.Kerdreux@imt-atlantique.fr>
License-Expression: GPL-3.0-or-later
Project-URL: Homepage, https://recherche.imt-atlantique.fr/xaal/
Project-URL: Documentation, https://gitlab.imt-atlantique.fr/xaal/code/python/-/blob/main/apps/fuse/README.rst
Project-URL: Source, https://gitlab.imt-atlantique.fr/xaal/code/python/-/tree/main/apps/fuse
Keywords: xaal,tools
Classifier: Programming Language :: Python
Classifier: Topic :: Home Automation
Requires-Dist: xaal.lib
Requires-Dist: xaal.monitor
Requires-Dist: xaal.schemas
Requires-Dist: fuse-python
